{
  "name": "Blackfish",
  "category": "patchouli:fish",
  "icon": "aquaculture:blackfish",
  "pages": [
    {
      "type": "patchouli:text",
      "text": "$(l)Stats$()$(li)Price: :coin: 24$(li)Season: Autumn/Winter$(li)Water: Ocean$(li)Weather: Any$(li)Time: Night in Autumn/Day or Night in Winter  $(br2)$(l)Notes$()$(br)"
    },
    {
      "type": "patchouli:entity",
      "entity": "aquaculture:blackfish",
      "scale": 0.8,
      "rotate": true,
      "text": "A shadowy deep-water fish that blends into the darkness and strikes without warning."
    }
  ]
}